LICENSE
MANIFEST.in
README.rst
setup.py
ssdb3.py
ssdb3.egg-info/PKG-INFO
ssdb3.egg-info/SOURCES.txt
ssdb3.egg-info/dependency_links.txt
ssdb3.egg-info/top_level.txt