Metadata-Version: 1.1
Name: ssdb3
Version: 0.0.1
Summary: An SSDB Client Library for Python3.
Home-page: https://github.com/daiooo/ssdb3
Author: daiooo
Author-email: d@d.com
License: BSD
Keywords: ssdb3
Platform: UNKNOWN
Classifier: Development Status :: 4 - Beta
Classifier: Programming Language :: Python
Classifier: Programming Language :: Python :: 3.6
Classifier: Programming Language :: Python :: 3.7
Classifier: Intended Audience :: Developers
Classifier: License :: OSI Approved :: BSD License
Classifier: Operating System :: POSIX
Classifier: Operating System :: POSIX :: Linux
Classifier: Topic :: Software Development :: Libraries :: Python Modules
